finalfusion-0.7.1.dist-info/RECORD
finalfusion-0.7.1.dist-info/WHEEL
finalfusion-0.7.1.dist-info/top_level.txt
finalfusion-0.7.1.dist-info/METADATA
finalfusion-0.7.1.dist-info/LICENSE
finalfusion-0.7.1.dist-info/entry_points.txt
finalfusion/py.typed
finalfusion/embeddings.py
finalfusion/io.py
finalfusion/norms.py
finalfusion/__init__.py
finalfusion/metadata.py
finalfusion/_util.py
finalfusion/vocab/vocab.py
finalfusion/vocab/subword.py
finalfusion/vocab/__init__.py
finalfusion/vocab/simple_vocab.py
finalfusion/scripts/bucket_to_explicit.py
finalfusion/scripts/similar.py
finalfusion/scripts/util.py
finalfusion/scripts/__init__.py
finalfusion/scripts/convert.py
finalfusion/scripts/analogy.py
finalfusion/compat/fasttext.py
finalfusion/compat/text.py
finalfusion/compat/word2vec.py
finalfusion/compat/__init__.py
finalfusion/storage/ndarray.py
finalfusion/storage/quantized.py
finalfusion/storage/__init__.py
finalfusion/storage/storage.py
finalfusion/subword/explicit_indexer.pyi
finalfusion/subword/hash_indexers.pyx
finalfusion/subword/endian.pxd
finalfusion/subword/ngrams.pyx
finalfusion/subword/ngrams.c
finalfusion/subword/explicit_indexer.cpython-36m-x86_64-linux-gnu.so
finalfusion/subword/ngrams.pyi
finalfusion/subword/hash_indexers.cpython-36m-x86_64-linux-gnu.so
finalfusion/subword/__init__.py
finalfusion/subword/fnv.pxd
finalfusion/subword/explicit_indexer.c
finalfusion/subword/ngrams.cpython-36m-x86_64-linux-gnu.so
finalfusion/subword/hash_indexers.c
finalfusion/subword/hash_indexers.pyi
finalfusion/subword/explicit_indexer.pyx
