Metadata-Version: 2.1
Name: finalfusion
Version: 0.7.1
Summary: Finalfusion in Python
Home-page: https://github.com/finalfusion/finalfusion-python
Author: Sebastian Pütz <seb.puetz@gmail.com>, Daniël de Kok <me@danieldk.eu>
License: BlueOak-1.0.0
Project-URL: Documentation, https://finalfusion-python.readthedocs.io/en/0.7.1
Project-URL: Finalfusion, https://finalfusion.github.io
Keywords: embeddings word2vec finalfusion finalfrontier fasttext glove
Platform: UNKNOWN
Classifier: Programming Language :: Python :: 3
Classifier: Operating System :: OS Independent
Classifier: Topic :: Text Processing :: Linguistic
Requires-Dist: numpy
Requires-Dist: toml
Requires-Dist: dataclasses
